clickpy/__init__.py
clickpy/__init__.pyi
clickpy/client.py
clickpy/client.pyi
clickpy/settings.py
clickpy/settings.pyi
clickpy/queries/__init__.py
clickpy/queries/__init__.pyi
clickpy/queries/base.py
clickpy/queries/base.pyi
clickpy/queries/keyword_downloads_resume_query.py
clickpy/queries/keyword_downloads_resume_query.pyi
clickpy/queries/keyword_packages_resume_query.py
clickpy/queries/keyword_packages_resume_query.pyi
clickpy/queries/keyword_releases_resume_query.py
clickpy/queries/keyword_releases_resume_query.pyi
clickpy/queries/keywords_by_releases_query.py
clickpy/queries/keywords_by_releases_query.pyi
clickpy/queries/package_downloads_by_version_query.py
clickpy/queries/package_downloads_by_version_query.pyi
clickpy/queries/package_downloads_per_month_query.py
clickpy/queries/package_downloads_per_month_query.pyi
clickpy/queries/package_downloads_resume_query.py
clickpy/queries/package_downloads_resume_query.pyi
clickpy/queries/package_releases_resume_query.py
clickpy/queries/package_releases_resume_query.pyi
clickpy/queries/tables_query.py
clickpy/queries/tables_query.pyi
clickpy_client-0.1.7.dist-info/METADATA
clickpy_client-0.1.7.dist-info/WHEEL
clickpy_client-0.1.7.dist-info/RECORD
