Metadata-Version: 2.4
Name: clickpy-client
Version: 0.1.7
Summary: Client for clickpy.clickhouse.com database
Author-email: Aleksei Marusich <aleksei.marusich@rocshers.com>
License: MIT
Keywords: clickhouse,pypi,rocshers
Classifier: License :: OSI Approved :: MIT License
Classifier: Programming Language :: Python
Classifier: Programming Language :: Python :: 3
Classifier: Programming Language :: Python :: 3 :: Only
Classifier: Programming Language :: Python :: 3.9
Classifier: Programming Language :: Python :: 3.10
Classifier: Programming Language :: Python :: 3.11
Classifier: Programming Language :: Python :: 3.12
Requires-Python: >=3.9
Requires-Dist: httpx>=0.15.0
Requires-Dist: pydantic-settings>=2.3.0
Requires-Dist: pydantic>=2.10.0
